LICENSE
README.md
setup.py
t9keyboard/__init__.py
t9keyboard/keyboard_keymap.py
t9keyboard/numpad_keyboard.py
t9keyboard/single_tap_keyboard_mode.py
t9keyboard/t9_mode.py
t9keyboard.egg-info/PKG-INFO
t9keyboard.egg-info/SOURCES.txt
t9keyboard.egg-info/dependency_links.txt
t9keyboard.egg-info/requires.txt
t9keyboard.egg-info/top_level.txt