Metadata-Version: 2.1
Name: t9keyboard
Version: 1.0.1
Summary: T9 Keyboard controlled by Numpad keyboard buttons.
Home-page: https://github.com/Edios/t9keyboard
Author: Miroslaw Lazarewicz
Author-email: miroslaw.lazarewicz@gmail.com
License: MIT
Classifier: Development Status :: 3 - Alpha
Classifier: Intended Audience :: Science/Research
Classifier: License :: OSI Approved :: MIT License
Classifier: Operating System :: Microsoft :: Windows
Classifier: Programming Language :: Python :: 3
Classifier: Programming Language :: Python :: 3.10
License-File: LICENSE
